<?xml version = '1.0' encoding = 'UTF-8'?>
<Diagram class="oracle.dbtools.crest.swingui.relational.DPVRelational" name="relational_model_ra4-2012" id="944BB637-7AF1-02F9-348D-DC43CCC7FC25">
<createdBy>Misa</createdBy>
<modifiedBy>Misa</modifiedBy>
<createdTime>2016-01-24 22:06:33 UTC</createdTime>
<autoRoute>false</autoRoute>
<boxInbox>true</boxInbox>
<showLegend>false</showLegend>
<showLabels>false</showLabels>
<showRelAttributes>false</showRelAttributes>
<gridEnabled>false</gridEnabled>
<showGrid>false</showGrid>
<diagramColor>-1</diagramColor>
<display>false</display>
<notation>1</notation>
<objectViews>
<OView class="oracle.dbtools.crest.swingui.relational.TVTable" oid="00078DF7-91E7-94DA-F870-95159E7B5818" otype="Table" vid="7159B809-80E1-83C6-F495-F41FDD221472">
<hideElementsInCurrentOnly>false</hideElementsInCurrentOnly>
<bounds x="1050" y="532" width="207" height="224"/>
</OView>
<OView class="oracle.dbtools.crest.swingui.relational.TVTable" oid="065BABC7-56D2-0535-605B-07977676DEC2" otype="Table" vid="C01ECF53-327F-8C9C-5311-EEA67986EFEB">
<hideElementsInCurrentOnly>false</hideElementsInCurrentOnly>
<bounds x="1367" y="517" width="130" height="58"/>
</OView>
<OView class="oracle.dbtools.crest.swingui.relational.TVTable" oid="2002703B-3EE2-904E-785E-5DD4A368B96C" otype="Table" vid="970577CE-E2D4-2797-6DDA-7912438BA636">
<hideElementsInCurrentOnly>false</hideElementsInCurrentOnly>
<bounds x="638" y="781" width="182" height="63"/>
</OView>
<OView class="oracle.dbtools.crest.swingui.relational.TVTable" oid="2290D7A6-48C2-37ED-F5E0-D8B7205CFFCF" otype="Table" vid="DEE3036B-DB1D-58F3-BC6F-1BAD6D69AF6E">
<hideElementsInCurrentOnly>false</hideElementsInCurrentOnly>
<bounds x="316" y="615" width="170" height="110"/>
</OView>
<OView class="oracle.dbtools.crest.swingui.relational.TVTable" oid="23CE214D-8D06-C0B5-6954-997648FABF1C" otype="Table" vid="62570111-78F3-C5E0-0024-AABD473FE58E">
<hideElementsInCurrentOnly>false</hideElementsInCurrentOnly>
<bounds x="1428" y="1009" width="196" height="59"/>
</OView>
<OView class="oracle.dbtools.crest.swingui.relational.TVTable" oid="3AE0CA31-8DAB-5D0E-AE6B-2F6D3773ACC3" otype="Table" vid="D7DDC4C2-6F47-86D2-D02C-BA13603007A1">
<hideElementsInCurrentOnly>false</hideElementsInCurrentOnly>
<bounds x="1375" y="605" width="172" height="82"/>
</OView>
<OView class="oracle.dbtools.crest.swingui.relational.TVTable" oid="602770C9-2697-BA7D-01BB-964ACC0928A1" otype="Table" vid="42094987-79DB-FB74-BE82-B7D85271C19D">
<hideElementsInCurrentOnly>false</hideElementsInCurrentOnly>
<bounds x="852" y="840" width="205" height="130"/>
</OView>
<OView class="oracle.dbtools.crest.swingui.relational.TVTable" oid="657EE1D8-0D64-676C-B15A-B4E12FC54D70" otype="Table" vid="1E2280A1-1CB9-C7C6-FEAB-9B0031CB324A">
<hideElementsInCurrentOnly>false</hideElementsInCurrentOnly>
<bounds x="631" y="1020" width="181" height="70"/>
</OView>
<OView class="oracle.dbtools.crest.swingui.relational.TVTable" oid="69AC1546-132C-3436-C1B0-D3A973DF8739" otype="Table" vid="D2C30C82-20BD-FEAA-3A51-9F6CB3DC4FB6">
<hideElementsInCurrentOnly>false</hideElementsInCurrentOnly>
<bounds x="1027" y="1010" width="175" height="67"/>
</OView>
<OView class="oracle.dbtools.crest.swingui.relational.TVTable" oid="7C961491-C3F7-22E2-0A7D-B5FB716BE841" otype="Table" vid="CEEA92AF-A898-5CDA-C828-63B7116B3CCB">
<hideElementsInCurrentOnly>false</hideElementsInCurrentOnly>
<bounds x="670" y="1320" width="195" height="65"/>
</OView>
<OView class="oracle.dbtools.crest.swingui.relational.TVTable" oid="8E8CCEC7-3DF9-1C78-95BB-79EDABFF3532" otype="Table" vid="80564FE1-E57E-6E3F-6B3F-AF8E5B7F9D45">
<hideElementsInCurrentOnly>false</hideElementsInCurrentOnly>
<bounds x="1632" y="431" width="127" height="63"/>
</OView>
<OView class="oracle.dbtools.crest.swingui.relational.TVTable" oid="A0C2D0BA-54C7-09E3-2242-B7FD7B6C68D0" otype="Table" vid="B6B6845E-60EA-3F6A-1005-C0327A3341E1">
<hideElementsInCurrentOnly>false</hideElementsInCurrentOnly>
<bounds x="399" y="389" width="140" height="79"/>
</OView>
<OView class="oracle.dbtools.crest.swingui.relational.TVTable" oid="B55A3A00-1154-54A5-6ACC-20C7E1933953" otype="Table" vid="6E5E0774-E786-C0F3-2BE7-C8BA2AA53BAA">
<hideElementsInCurrentOnly>false</hideElementsInCurrentOnly>
<bounds x="339" y="516" width="136" height="71"/>
</OView>
<OView class="oracle.dbtools.crest.swingui.relational.TVTable" oid="BCDFB37C-7868-0858-FE0A-42865A5E3FA5" otype="Table" vid="B0574305-7F06-8B81-7545-AFAB5BE0548C">
<hideElementsInCurrentOnly>false</hideElementsInCurrentOnly>
<bounds x="891" y="306" width="267" height="83"/>
</OView>
<OView class="oracle.dbtools.crest.swingui.relational.TVTable" oid="E5AE104A-AF18-391B-19DD-4DD1E076A8B2" otype="Table" vid="0AE0D145-BA98-2170-DF8B-DA35B5B017CF">
<hideElementsInCurrentOnly>false</hideElementsInCurrentOnly>
<bounds x="1008" y="1189" width="195" height="128"/>
</OView>
<OView class="oracle.dbtools.crest.swingui.relational.TVTable" oid="E70D1E41-2B04-7BAB-BD3E-E97931995D0D" otype="Table" vid="FF0C89CE-14F3-7A0E-1C09-2F93BD01A8E7">
<hideElementsInCurrentOnly>false</hideElementsInCurrentOnly>
<bounds x="1380" y="707" width="127" height="46"/>
</OView>
<OView class="oracle.dbtools.crest.swingui.relational.TVTable" oid="F093EFD1-2B40-49C0-1196-F36B4DAC6BC7" otype="Table" vid="8EF434B7-131E-F221-AC74-CD43AB12518D">
<hideElementsInCurrentOnly>false</hideElementsInCurrentOnly>
<bounds x="238" y="1089" width="232" height="220"/>
</OView>
<OView class="oracle.dbtools.crest.swingui.relational.TVTable" oid="FCC35E96-0FC6-1171-A4BD-B2CD44D18D35" otype="Table" vid="5EF77E83-3C39-D811-3A36-A3885ADFB721">
<hideElementsInCurrentOnly>false</hideElementsInCurrentOnly>
<bounds x="657" y="432" width="101" height="113"/>
</OView>
</objectViews>
<connectors>
<Connector class="oracle.dbtools.crest.swingui.relational.TVFKRelation" oid="0D136FAA-6748-BA19-532F-D0C520F63B13" otype="FKIndexAssociation" vid_source="B6B6845E-60EA-3F6A-1005-C0327A3341E1" vid_target="5EF77E83-3C39-D811-3A36-A3885ADFB721">
<hideElementsInCurrentOnly>false</hideElementsInCurrentOnly>
<lineWidth>1</lineWidth>
<points>
<point x="539" y="450"/>
<point x="657" y="450"/>
</points>
</Connector>
<Connector class="oracle.dbtools.crest.swingui.relational.TVFKRelation" oid="0EA8FEB2-DA44-7D5B-231A-C13A34DAFD70" otype="FKIndexAssociation" vid_source="970577CE-E2D4-2797-6DDA-7912438BA636" vid_target="5EF77E83-3C39-D811-3A36-A3885ADFB721">
<hideElementsInCurrentOnly>false</hideElementsInCurrentOnly>
<lineWidth>1</lineWidth>
<points>
<point x="707" y="781"/>
<point x="715" y="545"/>
</points>
</Connector>
<Connector class="oracle.dbtools.crest.swingui.relational.TVFKRelation" oid="1D6D3667-E9DA-C8C5-A04D-C2E6C3C1FC6B" otype="FKIndexAssociation" vid_source="970577CE-E2D4-2797-6DDA-7912438BA636" vid_target="1E2280A1-1CB9-C7C6-FEAB-9B0031CB324A">
<hideElementsInCurrentOnly>false</hideElementsInCurrentOnly>
<lineWidth>1</lineWidth>
<points>
<point x="725" y="844"/>
<point x="725" y="1020"/>
</points>
</Connector>
<Connector class="oracle.dbtools.crest.swingui.relational.TVFKRelation" oid="29B6A6CA-ECDC-ADDA-49FF-994696E86F2C" otype="FKIndexAssociation" vid_source="80564FE1-E57E-6E3F-6B3F-AF8E5B7F9D45" vid_target="C01ECF53-327F-8C9C-5311-EEA67986EFEB">
<hideElementsInCurrentOnly>false</hideElementsInCurrentOnly>
<lineWidth>1</lineWidth>
<points>
<point x="1632" y="462"/>
<point x="1497" y="546"/>
</points>
</Connector>
<Connector class="oracle.dbtools.crest.swingui.relational.TVFKRelation" oid="2B58D463-80AA-E159-C308-5760D4A4E50A" otype="FKIndexAssociation" vid_source="1E2280A1-1CB9-C7C6-FEAB-9B0031CB324A" vid_target="D2C30C82-20BD-FEAA-3A51-9F6CB3DC4FB6">
<hideElementsInCurrentOnly>false</hideElementsInCurrentOnly>
<lineWidth>1</lineWidth>
<points>
<point x="812" y="1048"/>
<point x="1027" y="1048"/>
</points>
</Connector>
<Connector class="oracle.dbtools.crest.swingui.relational.TVFKRelation" oid="2EFC0210-4B6E-D9DE-81F9-837F6E2086ED" otype="FKIndexAssociation" vid_source="7159B809-80E1-83C6-F495-F41FDD221472" vid_target="DEE3036B-DB1D-58F3-BC6F-1BAD6D69AF6E">
<hideElementsInCurrentOnly>false</hideElementsInCurrentOnly>
<lineWidth>1</lineWidth>
<points>
<point x="1050" y="670"/>
<point x="486" y="670"/>
</points>
</Connector>
<Connector class="oracle.dbtools.crest.swingui.relational.TVFKRelation" oid="3129C111-5D98-08E8-2427-30BF420D4059" otype="FKIndexAssociation" vid_source="7159B809-80E1-83C6-F495-F41FDD221472" vid_target="FF0C89CE-14F3-7A0E-1C09-2F93BD01A8E7">
<hideElementsInCurrentOnly>false</hideElementsInCurrentOnly>
<lineWidth>1</lineWidth>
<points>
<point x="1257" y="730"/>
<point x="1380" y="730"/>
</points>
</Connector>
<Connector class="oracle.dbtools.crest.swingui.relational.TVFKRelation" oid="31890503-7143-C2EE-0C2E-6E3A6A91FADC" otype="FKIndexAssociation" vid_source="42094987-79DB-FB74-BE82-B7D85271C19D" vid_target="7159B809-80E1-83C6-F495-F41FDD221472">
<hideElementsInCurrentOnly>false</hideElementsInCurrentOnly>
<lineWidth>1</lineWidth>
<points>
<point x="1053" y="840"/>
<point x="1053" y="756"/>
</points>
</Connector>
<Connector class="oracle.dbtools.crest.swingui.relational.TVFKRelation" oid="3DCC2316-7DD2-686C-5927-652A9D9D958E" otype="FKIndexAssociation" vid_source="FF0C89CE-14F3-7A0E-1C09-2F93BD01A8E7" vid_target="DEE3036B-DB1D-58F3-BC6F-1BAD6D69AF6E">
<hideElementsInCurrentOnly>false</hideElementsInCurrentOnly>
<lineWidth>1</lineWidth>
<points>
<point x="1380" y="716"/>
<point x="486" y="716"/>
</points>
</Connector>
<Connector class="oracle.dbtools.crest.swingui.relational.TVFKRelation" oid="401811F6-3064-3446-B8F9-B5DBDD74F87C" otype="FKIndexAssociation" vid_source="6E5E0774-E786-C0F3-2BE7-C8BA2AA53BAA" vid_target="5EF77E83-3C39-D811-3A36-A3885ADFB721">
<hideElementsInCurrentOnly>false</hideElementsInCurrentOnly>
<lineWidth>1</lineWidth>
<points>
<point x="475" y="530"/>
<point x="657" y="530"/>
</points>
</Connector>
<Connector class="oracle.dbtools.crest.swingui.relational.TVFKRelation" oid="5378B6E4-ECE5-C3CA-8D56-F81479DBE452" otype="FKIndexAssociation" vid_source="62570111-78F3-C5E0-0024-AABD473FE58E" vid_target="8EF434B7-131E-F221-AC74-CD43AB12518D">
<hideElementsInCurrentOnly>false</hideElementsInCurrentOnly>
<lineWidth>1</lineWidth>
<points>
<point x="1447" y="1068"/>
<point x="470" y="1199"/>
</points>
</Connector>
<Connector class="oracle.dbtools.crest.swingui.relational.TVFKRelation" oid="60994902-1D5D-D47D-B1B0-BC76378EF07D" otype="FKIndexAssociation" vid_source="FF0C89CE-14F3-7A0E-1C09-2F93BD01A8E7" vid_target="7159B809-80E1-83C6-F495-F41FDD221472">
<hideElementsInCurrentOnly>false</hideElementsInCurrentOnly>
<lineWidth>1</lineWidth>
<points>
<point x="1380" y="730"/>
<point x="1257" y="730"/>
</points>
</Connector>
<Connector class="oracle.dbtools.crest.swingui.relational.TVFKRelation" oid="64731FE7-1B29-3F43-8B50-B6EA921C2051" otype="FKIndexAssociation" vid_source="7159B809-80E1-83C6-F495-F41FDD221472" vid_target="8EF434B7-131E-F221-AC74-CD43AB12518D">
<hideElementsInCurrentOnly>false</hideElementsInCurrentOnly>
<lineWidth>1</lineWidth>
<points>
<point x="1050" y="644"/>
<point x="470" y="1089"/>
</points>
</Connector>
<Connector class="oracle.dbtools.crest.swingui.relational.TVFKRelation" oid="72CB6BD3-9E71-C079-F58D-323372DC8666" otype="FKIndexAssociation" vid_source="CEEA92AF-A898-5CDA-C828-63B7116B3CCB" vid_target="8EF434B7-131E-F221-AC74-CD43AB12518D">
<hideElementsInCurrentOnly>false</hideElementsInCurrentOnly>
<lineWidth>1</lineWidth>
<points>
<point x="865" y="1320"/>
<point x="470" y="1283"/>
</points>
</Connector>
<Connector class="oracle.dbtools.crest.swingui.relational.TVFKRelation" oid="7943AC7C-17BE-EB2A-4577-4397A61324ED" otype="FKIndexAssociation" vid_source="7159B809-80E1-83C6-F495-F41FDD221472" vid_target="D7DDC4C2-6F47-86D2-D02C-BA13603007A1">
<hideElementsInCurrentOnly>false</hideElementsInCurrentOnly>
<lineWidth>1</lineWidth>
<points>
<point x="1257" y="646"/>
<point x="1375" y="646"/>
</points>
</Connector>
<Connector class="oracle.dbtools.crest.swingui.relational.TVFKRelation" oid="86335823-FE82-54AA-189E-8D87B6CD2A4E" otype="FKIndexAssociation" vid_source="C01ECF53-327F-8C9C-5311-EEA67986EFEB" vid_target="D7DDC4C2-6F47-86D2-D02C-BA13603007A1">
<hideElementsInCurrentOnly>false</hideElementsInCurrentOnly>
<lineWidth>1</lineWidth>
<points>
<point x="1436" y="575"/>
<point x="1436" y="605"/>
</points>
</Connector>
<Connector class="oracle.dbtools.crest.swingui.relational.TVFKRelation" oid="979C0F21-BDCA-405D-CAA4-A83FDD7B89EE" otype="FKIndexAssociation" vid_source="62570111-78F3-C5E0-0024-AABD473FE58E" vid_target="7159B809-80E1-83C6-F495-F41FDD221472">
<hideElementsInCurrentOnly>false</hideElementsInCurrentOnly>
<lineWidth>1</lineWidth>
<points>
<point x="1428" y="1009"/>
<point x="1257" y="756"/>
</points>
</Connector>
<Connector class="oracle.dbtools.crest.swingui.relational.TVFKRelation" oid="BC3CBF9F-A502-206A-C130-8A8B6F7076DA" otype="FKIndexAssociation" vid_source="7159B809-80E1-83C6-F495-F41FDD221472" vid_target="C01ECF53-327F-8C9C-5311-EEA67986EFEB">
<hideElementsInCurrentOnly>false</hideElementsInCurrentOnly>
<lineWidth>1</lineWidth>
<points>
<point x="1257" y="563"/>
<point x="1367" y="563"/>
</points>
</Connector>
<Connector class="oracle.dbtools.crest.swingui.relational.TVFKRelation" oid="BDA910F3-9DA9-105C-E987-20131061A429" otype="FKIndexAssociation" vid_source="62570111-78F3-C5E0-0024-AABD473FE58E" vid_target="5EF77E83-3C39-D811-3A36-A3885ADFB721">
<hideElementsInCurrentOnly>false</hideElementsInCurrentOnly>
<lineWidth>1</lineWidth>
<points>
<point x="1428" y="1009"/>
<point x="758" y="545"/>
</points>
</Connector>
<Connector class="oracle.dbtools.crest.swingui.relational.TVFKRelation" oid="CA6CBABB-A0F1-9DCD-098E-92DDDB97E451" otype="FKIndexAssociation" vid_source="62570111-78F3-C5E0-0024-AABD473FE58E" vid_target="42094987-79DB-FB74-BE82-B7D85271C19D">
<hideElementsInCurrentOnly>false</hideElementsInCurrentOnly>
<lineWidth>1</lineWidth>
<points>
<point x="1428" y="1009"/>
<point x="1057" y="970"/>
</points>
</Connector>
<Connector class="oracle.dbtools.crest.swingui.relational.TVFKRelation" oid="CAA89644-4206-37CE-6ADA-04630BC13CE9" otype="FKIndexAssociation" vid_source="D2C30C82-20BD-FEAA-3A51-9F6CB3DC4FB6" vid_target="62570111-78F3-C5E0-0024-AABD473FE58E">
<hideElementsInCurrentOnly>false</hideElementsInCurrentOnly>
<lineWidth>1</lineWidth>
<points>
<point x="1202" y="1049"/>
<point x="1428" y="1049"/>
</points>
</Connector>
<Connector class="oracle.dbtools.crest.swingui.relational.TVFKRelation" oid="CE7CE4EA-8C8A-1601-BCDF-48C7D6391986" otype="FKIndexAssociation" vid_source="B0574305-7F06-8B81-7545-AFAB5BE0548C" vid_target="7159B809-80E1-83C6-F495-F41FDD221472">
<hideElementsInCurrentOnly>false</hideElementsInCurrentOnly>
<lineWidth>1</lineWidth>
<points>
<point x="1104" y="389"/>
<point x="1104" y="532"/>
</points>
</Connector>
<Connector class="oracle.dbtools.crest.swingui.relational.TVFKRelation" oid="DBF6E7E8-810A-AD6B-3DC3-C7B97C8FD0F3" otype="FKIndexAssociation" vid_source="62570111-78F3-C5E0-0024-AABD473FE58E" vid_target="0AE0D145-BA98-2170-DF8B-DA35B5B017CF">
<hideElementsInCurrentOnly>false</hideElementsInCurrentOnly>
<lineWidth>1</lineWidth>
<points>
<point x="1428" y="1068"/>
<point x="1203" y="1189"/>
</points>
</Connector>
<Connector class="oracle.dbtools.crest.swingui.relational.TVFKRelation" oid="E8399C2C-02FD-857E-B954-F7E06F9C76DA" otype="FKIndexAssociation" vid_source="5EF77E83-3C39-D811-3A36-A3885ADFB721" vid_target="8EF434B7-131E-F221-AC74-CD43AB12518D">
<hideElementsInCurrentOnly>false</hideElementsInCurrentOnly>
<lineWidth>1</lineWidth>
<points>
<point x="680" y="545"/>
<point x="354" y="1089"/>
</points>
</Connector>
<Connector class="oracle.dbtools.crest.swingui.relational.TVFKRelation" oid="F6114489-2584-771B-F97C-3C73746C3D14" otype="FKIndexAssociation" vid_source="0AE0D145-BA98-2170-DF8B-DA35B5B017CF" vid_target="8EF434B7-131E-F221-AC74-CD43AB12518D">
<hideElementsInCurrentOnly>false</hideElementsInCurrentOnly>
<lineWidth>1</lineWidth>
<points>
<point x="1153" y="1189"/>
<point x="470" y="1235"/>
</points>
</Connector>
</connectors>
</Diagram>